{
    "name": "Helmet",
    "fields": [
        {
            "fieldName": "name",
            "fieldType": "String"
        },
        {
            "fieldName": "effect",
            "fieldType": "String"
        },
        {
            "fieldName": "price",
            "fieldType": "Integer"
        },
        {
            "fieldName": "defence",
            "fieldType": "Integer"
        },
        {
            "fieldName": "part",
            "fieldType": "String"
        }
    ],
    "relationships": [
        {
            "relationshipType": "one-to-many",
            "relationshipName": "character",
            "otherEntityName": "character",
            "otherEntityRelationshipName": "helmet"
        },
        {
            "relationshipType": "many-to-many",
            "otherEntityRelationshipName": "helmet",
            "relationshipName": "shop",
            "otherEntityName": "shop",
            "otherEntityField": "id",
            "ownerSide": true
        }
    ],
    "changelogDate": "20181121211730",
    "entityTableName": "helmet",
    "dto": "mapstruct",
    "pagination": "no",
    "service": "serviceImpl",
    "jpaMetamodelFiltering": false,
    "fluentMethods": true,
    "clientRootFolder": "",
    "applications": "*"
}